acace_context_storage/__init__.py
acace_context_storage-0.1.0.dist-info/METADATA
acace_context_storage-0.1.0.dist-info/WHEEL
acace_context_storage-0.1.0.dist-info/RECORD
