Metadata-Version: 2.3
Name: acace_context_storage
Version: 0.1.0
Summary: Context storage utilities for ACACE
Author: ACACE Team
Author-email: team@acace.ai
Requires-Python: >=3.8,<4.0
Classifier: Programming Language :: Python :: 3
Classifier: Programming Language :: Python :: 3.8
Classifier: Programming Language :: Python :: 3.9
Classifier: Programming Language :: Python :: 3.10
Classifier: Programming Language :: Python :: 3.11
Classifier: Programming Language :: Python :: 3.12
Classifier: Programming Language :: Python :: 3.13
Requires-Dist: numpy (>=1.26.3,<2.0.0)
Requires-Dist: pymongo (>=4.6.1,<5.0.0)
Requires-Dist: redis (>=5.0.1,<6.0.0)
Requires-Dist: sqlalchemy (>=2.0.25,<3.0.0)
